<annotation>
	<folder>train</folder>
	<filename>BikesHelmets304_png_jpg.rf.ff231692f018f69db9217cd844652645.jpg</filename>
	<path>D:\helmet detector\data (1)\train\BikesHelmets304_png_jpg.rf.ff231692f018f69db9217cd844652645.jpg</path>
	<source>
		<database>Unknown</database>
	</source>
	<size>
		<width>416</width>
		<height>416</height>
		<depth>3</depth>
	</size>
	<segmented>0</segmented>
	<object>
		<name>No Helmet</name>
		<pose>Unspecified</pose>
		<truncated>0</truncated>
		<difficult>0</difficult>
		<bndbox>
			<xmin>315</xmin>
			<ymin>79</ymin>
			<xmax>348</xmax>
			<ymax>134</ymax>
		</bndbox>
	</object>
	<object>
		<name>No Helmet</name>
		<pose>Unspecified</pose>
		<truncated>0</truncated>
		<difficult>0</difficult>
		<bndbox>
			<xmin>276</xmin>
			<ymin>92</ymin>
			<xmax>294</xmax>
			<ymax>128</ymax>
		</bndbox>
	</object>
	<object>
		<name>No Helmet</name>
		<pose>Unspecified</pose>
		<truncated>0</truncated>
		<difficult>0</difficult>
		<bndbox>
			<xmin>253</xmin>
			<ymin>99</ymin>
			<xmax>272</xmax>
			<ymax>135</ymax>
		</bndbox>
	</object>
	<object>
		<name>No Helmet</name>
		<pose>Unspecified</pose>
		<truncated>0</truncated>
		<difficult>0</difficult>
		<bndbox>
			<xmin>135</xmin>
			<ymin>105</ymin>
			<xmax>158</xmax>
			<ymax>137</ymax>
		</bndbox>
	</object>
	<object>
		<name>No Helmet</name>
		<pose>Unspecified</pose>
		<truncated>0</truncated>
		<difficult>0</difficult>
		<bndbox>
			<xmin>117</xmin>
			<ymin>105</ymin>
			<xmax>133</xmax>
			<ymax>139</ymax>
		</bndbox>
	</object>
	<object>
		<name>No Helmet</name>
		<pose>Unspecified</pose>
		<truncated>0</truncated>
		<difficult>0</difficult>
		<bndbox>
			<xmin>49</xmin>
			<ymin>83</ymin>
			<xmax>78</xmax>
			<ymax>139</ymax>
		</bndbox>
	</object>
	<object>
		<name>No Helmet</name>
		<pose>Unspecified</pose>
		<truncated>0</truncated>
		<difficult>0</difficult>
		<bndbox>
			<xmin>14</xmin>
			<ymin>86</ymin>
			<xmax>43</xmax>
			<ymax>140</ymax>
		</bndbox>
	</object>
</annotation>
