<annotation>
	<folder>train</folder>
	<filename>BikesHelmets84_png_jpg.rf.8461aa9c358cbf1805d8be0eee3b9b16.jpg</filename>
	<path>D:\helmet detector\data (1)\train\BikesHelmets84_png_jpg.rf.8461aa9c358cbf1805d8be0eee3b9b16.jpg</path>
	<source>
		<database>Unknown</database>
	</source>
	<size>
		<width>416</width>
		<height>416</height>
		<depth>3</depth>
	</size>
	<segmented>0</segmented>
	<object>
		<name>Helmet</name>
		<pose>Unspecified</pose>
		<truncated>0</truncated>
		<difficult>0</difficult>
		<bndbox>
			<xmin>119</xmin>
			<ymin>89</ymin>
			<xmax>203</xmax>
			<ymax>178</ymax>
		</bndbox>
	</object>
</annotation>
