<annotation>
	<folder>train</folder>
	<filename>BikesHelmets523_png_jpg.rf.cc127199dde6e3eff2d4fa977c97a887.jpg</filename>
	<path>D:\helmet detector\data (1)\train\BikesHelmets523_png_jpg.rf.cc127199dde6e3eff2d4fa977c97a887.jpg</path>
	<source>
		<database>Unknown</database>
	</source>
	<size>
		<width>416</width>
		<height>416</height>
		<depth>3</depth>
	</size>
	<segmented>0</segmented>
	<object>
		<name>No Helmet</name>
		<pose>Unspecified</pose>
		<truncated>0</truncated>
		<difficult>0</difficult>
		<bndbox>
			<xmin>183</xmin>
			<ymin>67</ymin>
			<xmax>219</xmax>
			<ymax>108</ymax>
		</bndbox>
	</object>
	<object>
		<name>No Helmet</name>
		<pose>Unspecified</pose>
		<truncated>0</truncated>
		<difficult>0</difficult>
		<bndbox>
			<xmin>283</xmin>
			<ymin>42</ymin>
			<xmax>322</xmax>
			<ymax>94</ymax>
		</bndbox>
	</object>
</annotation>
